{
    "fileList": [
        {
            "fileName": "./db/f1.txt",
            "fileNameHash":"",
            "fileContentHash":"",
            "timeStamp":"",
            "permission": "p",
            "createdBy": "saiteja",
            "userList": [
                ""
            ]
        },
        {
            "fileName": "./db/f2.txt",
            "fileNameHash":"",
            "fileContentHash":"",
            "timeStamp":"",
            "permission": "p",
            "createdBy": "saiteja",
            "userList": [
                ""
            ]
        },
        {
            "fileName": "./db/f3.txt",
            "fileNameHash":"",
            "fileContentHash":"",
            "timeStamp":"",
            "permission": "p",
            "createdBy": "saiteja",
            "userList": [
                ""
            ]
        }
    ]
}